tsp_solver_Tasnim/__init__.py
tsp_solver_Tasnim/utils.py
tsp_solver_Tasnim/algorithms/Asearch.py
tsp_solver_Tasnim/algorithms/__init__.py
tsp_solver_Tasnim/algorithms/hill_climbing.py
tsp_solver_Tasnim/algorithms/random_search.py
tsp_solver_Tasnim/algorithms/simulated_annealing.py
tsp_solver_Tasnim-0.1.0.dist-info/METADATA
tsp_solver_Tasnim-0.1.0.dist-info/WHEEL
tsp_solver_Tasnim-0.1.0.dist-info/top_level.txt
tsp_solver_Tasnim-0.1.0.dist-info/RECORD
